autoprocess/clean.py
autoprocess/transformation.py
autoprocess/visualization.py
autoprocess-1.0.0.dist-info/LICENSE.py
autoprocess-1.0.0.dist-info/METADATA
autoprocess-1.0.0.dist-info/WHEEL
autoprocess-1.0.0.dist-info/top_level.txt
autoprocess-1.0.0.dist-info/RECORD
